Metadata-Version: 1.2
Name: pghstore
Version: 2.0.2
Summary: PostgreSQL hstore formatter
Home-page: https://github.com/heroku/pghstore
Author: Hong Minhee
Author-email: minhee@dahlia.kr
Maintainer: Salesforce.com, Inc
License: MIT License
Platform: any
Classifier: Development Status :: 4 - Beta
Classifier: Intended Audience :: Developers
Classifier: License :: OSI Approved :: MIT License
Classifier: Operating System :: OS Independent
Classifier: Programming Language :: Python :: 2.5
Classifier: Programming Language :: Python :: 2.6
Classifier: Programming Language :: Python :: 2.7
Classifier: Programming Language :: Python :: 2 :: Only
Classifier: Programming Language :: Python :: Implementation :: CPython
Classifier: Programming Language :: Python :: Implementation :: PyPy
Classifier: Programming Language :: Python :: Implementation :: Stackless
Classifier: Topic :: Database
Classifier: Topic :: Software Development :: Libraries :: Python Modules
